{"input":{},"actions":[{"name":"Login của BO","function":"o9.core.template.templateDownload","type":"java","para":[],"status":"A","response":{"true":{"fo":[{"txcode":"#sys:fo-msg-toast","input":{"lang":"sysActionOk"}}]},"false":{"fo":[{"txcode":"#sys:fo-msg-toast","input":{"lang":"loginFaild"}}]}}}],"status":"A","txtype":"bo","txcode":"bo-button-print","txname":"bo-button-print","version":3,"updateTime":1596697957450,"hasRole":"false","isOld":true,"response":{"fo":[{"txcode":"","input":{}}]},"order":7}